{
  "coverage": "82.24%",
  "expectCount": 321,
  "actualCount": 264,
  "files": {
    "transpiled/datetime.js": {
      "expectCount": 100,
      "actualCount": 100,
      "undocumentLines": []
    },
    "transpiled/duration.js": {
      "expectCount": 40,
      "actualCount": 40,
      "undocumentLines": []
    },
    "transpiled/errors.js": {
      "expectCount": 10,
      "actualCount": 10,
      "undocumentLines": []
    },
    "transpiled/impl/formatter.js": {
      "expectCount": 14,
      "actualCount": 1,
      "undocumentLines": [
        44,
        45,
        46,
        48,
        51,
        101,
        104,
        111,
        115,
        119,
        123,
        134,
        330
      ]
    },
    "transpiled/impl/locale.js": {
      "expectCount": 47,
      "actualCount": 3,
      "undocumentLines": [
        127,
        129,
        130,
        136,
        139,
        156,
        171,
        189,
        192,
        201,
        211,
        230,
        232,
        235,
        243,
        258,
        259,
        260,
        261,
        262,
        263,
        264,
        265,
        266,
        267,
        269,
        275,
        281,
        287,
        290,
        303,
        311,
        314,
        317,
        326,
        337,
        352,
        363,
        372,
        375,
        378,
        381,
        386,
        391
      ]
    },
    "transpiled/info.js": {
      "expectCount": 11,
      "actualCount": 11,
      "undocumentLines": []
    },
    "transpiled/interval.js": {
      "expectCount": 39,
      "actualCount": 39,
      "undocumentLines": []
    },
    "transpiled/settings.js": {
      "expectCount": 12,
      "actualCount": 12,
      "undocumentLines": []
    },
    "transpiled/zone.js": {
      "expectCount": 9,
      "actualCount": 9,
      "undocumentLines": []
    },
    "transpiled/zones/fixedOffsetZone.js": {
      "expectCount": 13,
      "actualCount": 13,
      "undocumentLines": []
    },
    "transpiled/zones/IANAZone.js": {
      "expectCount": 16,
      "actualCount": 16,
      "undocumentLines": []
    },
    "transpiled/zones/systemZone.js": {
      "expectCount": 10,
      "actualCount": 10,
      "undocumentLines": []
    }
  }
}